playitagainsam/__init__.py
playitagainsam/__main__.py
playitagainsam/coordinator.py
playitagainsam/eventlog.py
playitagainsam/player.py
playitagainsam/recorder.py
playitagainsam/util.py
playitagainsam-0.6.0.data/scripts/pias
playitagainsam-0.6.0.dist-info/LICENSE.txt
playitagainsam-0.6.0.dist-info/METADATA
playitagainsam-0.6.0.dist-info/WHEEL
playitagainsam-0.6.0.dist-info/top_level.txt
playitagainsam-0.6.0.dist-info/RECORD
