Metadata-Version: 2.1
Name: playitagainsam
Version: 0.6.0
Summary: record and replay interactive terminal sessions
Home-page: https://github.com/rfk/playitagainsam
Author: Ryan Kelly
Author-email: ryan@rfk.id.au
License: MIT
Keywords: shell record presentation tutorial
Platform: UNKNOWN
Classifier: Programming Language :: Python
Classifier: Programming Language :: Python :: 2
Classifier: Programming Language :: Python :: 2.7
Classifier: Programming Language :: Python :: 3
Classifier: Programming Language :: Python :: 3.5
Classifier: License :: OSI Approved
Classifier: License :: OSI Approved :: MIT License
Classifier: Development Status :: 4 - Beta
Classifier: Intended Audience :: Developers
Requires-Dist: psutil (>=2.0)
Requires-Dist: six
